pybrook-0.1.7.dist-info/METADATA
pybrook-0.1.7.dist-info/WHEEL
pybrook-0.1.7.dist-info/entry_points.txt
pybrook-0.1.7.dist-info/licenses/LICENSE.md
pybrook/__init__.py
pybrook/__main__.py
pybrook/config.py
pybrook/consumers/__init__.py
pybrook/consumers/base.py
pybrook/consumers/field_generator.py
pybrook/consumers/worker.py
pybrook/encoding.py
pybrook/examples/__init__.py
pybrook/examples/demo.py
pybrook/examples/ztm.py
pybrook/frontend/build/bundle.css
pybrook/frontend/build/bundle.js
pybrook/frontend/build/bundle.js.map
pybrook/frontend/favicon.png
pybrook/frontend/global.css
pybrook/frontend/index.html
pybrook/models.py
pybrook/redis_plugin_integration.py
pybrook/schemas.py
pybrook-0.1.7.dist-info/RECORD
