Metadata-Version: 2.1
Name: pybrook
Version: 0.1.7
Summary: PyBrook - a real-time cloud computing framework for the Internet of Things.
Author-Email: =?utf-8?q?Micha=C5=82_Rokita?= <mrokita@mrokita.pl>
License: GPL-3.0-or-later
Project-URL: Repository, https://github.com/pybrook/pybrook
Requires-Python: <4.0,>=3.9
Requires-Dist: fastapi<1.0.0,>=0.95.2
Requires-Dist: uvicorn[standard]<1.0.0,>=0.22.0
Requires-Dist: redis[asyncio]<5.0.0,>=4.5.5
Requires-Dist: loguru<1.0.0,>=0.7.0
Requires-Dist: gunicorn<21.0.0,>=20.1.0
Requires-Dist: watchdog<4.0.0,>=3.0.0
Requires-Dist: uvloop<1.0.0,>=0.19.0
Requires-Dist: orjson<4.0.0,>=3.8.7
Requires-Dist: pydantic<2.0.0,>=1.10.8
Requires-Dist: pyyaml!=5.4.0,!=5.4.1,!=6.0.0
